<glazes
    xmlns="tag:fenglich.fastmail.fm,2007:Pottery"
    xmlns:xi="http://www.w3.org/2001/XInclude">
    <glaze xml:id="GreenHue"
           manufacturer="Potterycrafts Limited"
           name="Green Hue"
           productID="P2579"/>

    <glaze xml:id="FrostedJade"
           manufacturer="Potterycrafts Limited"
           name="Frosted Jade"
           productID="P2540"/>

    <glaze xml:id="IntenseBlack"
           manufacturer="Potterycrafts Limited"
           name="Intense Black"
           productID="P3555"/>

    <glaze xml:id="WhiteGloss"
           manufacturer="Potterycrafts Limited"
           name="White Gloss"
           productID="P3550"/>

    <glaze xml:id="SandBrown"
           manufacturer="Potterycrafts Limited"
           name="Sand Brown, B/O"
           type="BrushOn"
           productID="P2845.5"/>

    <glaze xml:id="ImagineGreen"
           manufacturer="Ceradel"
           name="Green, Imagine ELG 80, Vent 230 ML Green"
           type="BrushOn"
           description="Brush on."/>

    <glaze xml:id="GreyAmaco"
           name="Grey, Sahara Liquid Glazes, HF series"
           productID="HF-18"
           manufacturer="Amaco"
           type="BrushOn"
           description="Brush on glaze."/>

    <glaze xml:id="YellowBO"
           name="Yellow Brush-on glaze"
           productID="P2842"
           manufacturer="Potterycrafts Limited"
           type="BrushOn"
           description="Brush on glaze."/>

    <glaze xml:id="AxnerBlackUnderGlazePen"
           name="Black underglaze pen"
           productID="P4001"
           manufacturer="AXNER"
           type="BrushOn"
           description="Pre-mixed on bottle, to 1280C."/>

    <glaze xml:id="Transparent"
           name="Transparent"
           productID="P1091"
           manufacturer="Unknown"
           description="Can't be found in Waldermar Ellefesen's price catalog from 2003, nor does the number show up in Potterycrafts' info. Is a porcelain glaze, according to Sissel."/>

    <glaze xml:id="TransparentCobberCarbonate"
           name="Cobber Carbonate oxide in transparent glaze"
           manufacturer="Mixture"
           description="To 200 ml transparent glaze, P1091, was 20 g Cobber carbonate, P3404, added." />

    <glaze xml:id="TransparentYellowStain"
           name="Yellow stain in transparent glaze"
           manufacturer="Mixture"
           description="To 200 ml transparent glaze, P1091 was 20 g Canary/Golden Yellow, P4140, added." />

   <glaze xml:id="Chocolate"
       name="Black stain in transparent glaze"
       manufacturer="Mixture"
       description="To 200 ml transparent glaze, P1091 was 20 g Black stain, P4130, added." />

   <glaze xml:id="GreenHueAndFrostedJade"
       name="Green Hue mixed with Frosted jade"
       manufacturer="Mixture"
       description="100 ml Green Hue at gravity 45 mixed with 100 ml Frosted Jade at gravity 44." />

   <glaze xml:id="AmacoWhiteBO"
       name="White"
       productID="HF-11A White"
       manufacturer="Amaco"
       type="BrushOn"
       description="Sahara Liquid Glazes, HF-11 White. Brush-on."/>

   <glaze xml:id="AmacoWaxyWhite"
       name="Waxy White"
       productID="HF-17"
       manufacturer="Amaco"
       type="BrushOn"
       description="Sahara Liquid Glazes, HF-17 Waxy White. Brush-on."/>

   <glaze xml:id="RedBO"
       name="Red brush on"
       productID="P2840"
       manufacturer="Potterycrafts Limited"
       type="BrushOn"
       description="Red brush on"/>

   <glaze xml:id="TurquoiseBO"
       name="Turquoise, Sahara Liquid Series"
       productID="HF-26"
       type="BrushOn"
       manufacturer="Amaco"/>

   <glaze xml:id="WhiteBO"
      name="White Brush-on"
      productID="2850.5"
      type="BrushOn"
      manufacturer="Potterycrafts Limited"/>

   <glaze xml:id="IndigoBlue"
      name="Indigo Blue"
      productID="2844.5"
      type="BrushOn"
      manufacturer="Potterycrafts Limited"/>

   <glaze xml:id="OilSpot"
      name="Oil Spot, Potter's Choice Liquid Glazes"
      productID="PC-35"
      type="BrushOn"
      manufacturer="Amaco"/>

   <glaze xml:id="TexturedBlue"
      name="Textured Blue, Sahara Liquid Glaze"
      productID="HF-22"
      type="BrushOn"
      manufacturer="Amaco"/>

   <glaze xml:id="GoldBrownBO"
      name="Gold Brown Brush-on"
      productID="2847.5"
      type="BrushOn"
      manufacturer="Potterycrafts Limited"/>

   <glaze xml:id="VelourBlackBO"
      name="Velour Black, V Series, Velvet Underglaze"
      productID="V-370"
      type="BrushOn"
      manufacturer="Amaco"/>

   <glaze xml:id="CeradelNoir"
      name="Noir, Imagine"
      productID="ELG 60"
      manufacturer="Ceradel"
      type="BrushOn"
      description="Brush on."/>

   <glaze xml:id="AmacoWhiteUnderglaze"
      name="White, V Series, Velvet Underglaze"
      productID="V-360"
      type="BrushOn"
      manufacturer="Ceradel"/>

   <glaze xml:id="BlackBO"
           manufacturer="Potterycrafts Limited"
           name="Black Brush-on"
           type="BrushOn"
           productID="P2851"/>

   <glaze xml:id="LichenGreenBO"
           manufacturer="Potterycrafts Limited"
           name="Lichen Green"
           type="BrushOn"
           productID="P2822"/>

   <glaze xml:id="OrangeBO"
           manufacturer="Potterycrafts Limited"
           name="Orange brush-on"
           type="BrushOn"
           productID="P2841"/>

   <glaze xml:id="JetBlack"
           manufacturer="Amaco"
           name="Jet Black, Velvet Underglaze, V Series"
           type="BrushOn"
           productID="V-361"/>

   <glaze xml:id="AmacoBrown"
           manufacturer="Amaco"
           name="Brown, Sahara Liquid Series, HF-Series"
           type="BrushOn"
           productID="HF-30"/>

   <glaze xml:id="YellowOatMetal"
           manufacturer="Amaco"
           name="Matt Yellow Oat Metal, Sahara Liquid Series, HF-Series"
           type="BrushOn"
           productID="HF-62"/>

   <glaze xml:id="TexturedTan"
           manufacturer="Amaco"
           name="Textured Tan, Sahara Liquid Series, HF-Series"
           type="BrushOn"
           productID="HF-32"/>

   <glaze xml:id="AmacoYellow"
           manufacturer="Amaco"
           name="Yellow, Sahara Liquid Series, HF-Series"
           type="BrushOn"
           productID="HF-60"/>

   <glaze xml:id="TransparentBO"
           manufacturer="Potterycrafts Limited"
           name="Transparent brush-on"
           type="BrushOn"
           productID="P2793"/>

       <!-- WTF? TODO Aluminium Oxide as Silica??? -->
   <glaze xml:id="RawBaseLeach"
           manufacturer="Frans Englich"
           name="Leach Base Glaze"
           description="40 Custer Feldspar(Kalifeltspat, P3316), Silica 30(Aluminium oxide, P3300), Whiting 20(P3346), Kaolin 10(Flint P3319)."/>

   <glaze xml:id="WhiteLeach"
           manufacturer="Frans Englich"
           name="White Leach"
           description="40 Custer Feldspar(Kalifeltspat, P3316), Silica 30(Aluminium oxide, P3300), Whiting 20(P3346), Kaolin 10(Flint P3319), and 10 zirconium oxide(R1026). 110 parts in total, in other words."/>
   <glaze xml:id="WhiterLeach"
           manufacturer="Frans Englich"
           name="Whiter Leach"
           description="40 Custer Feldspar(Kalifeltspat, P3316), Silica 30(Aluminium oxide, P3300), Whiting 20(P3346), Kaolin 10(Flint P3319), and 20 zirconium oxide(R1026). 120 parts in total, in other words."/>
       <glaze xml:id="BlueWhiterLeach"
           manufacturer="Frans Englich"
           name="Blue Whiter Leach"
           description="40 Custer Feldspar(Kalifeltspat, P3316), Silica 30(Aluminium oxide, P3300), Whiting 20(P3346), Kaolin 10(Flint P3319), and 20 zirconium oxide(R1026), 1 Cobolt Oxide. 121 parts in total, in other words."/>

   <glaze xml:id="CandaceBlack"
           manufacturer="Frans Englich"
           name="Candace Black"
           description="Candace Black from The Complete Guide to High-Fire Glazes, p. 127, also listed on p. 76. 65 F-4 Feldspar, 5 Whiting, 20 Silica, 5 Kaolin, 5 Dolomite, 8 Red Iron Oxide, 5 Cobalt Carbonate. Used instead Carbonate Oxide(P3403), Aluminium Oxide(P3300) as Kaolin, Red Synthetic Iron Oxide(P3441), Flint(P3319) as Silica, Feldspar FFF(P3316) as F-4 Feldspar."/>

   <glaze xml:id="ModifiedTransparentGreen"
           manufacturer="Frans Englich"
           name="Transparent Green"
           description='Transparent Green "base" from The Complete Guide to High-Fire Glazes, p. 98, but using Tin Oxide instead of Zinc Oxide. 70 Cornwall Stone, Whiting 10, Grolleg Kaolin 10, Tin Oxide 10, Copper Carbonate 4. Instead of Grolleg Kaolin(whatever that is) was Aluminium Oxide(P3300) used.'/>

   <glaze xml:id="WillsOribe"
           manufacturer="Frans Englich"
           name="Will's Oribe"
           productID="WillsOribe"
           description="Will's Oribe from The Complete Guide to High-Fire Glazes, p. 101. Custer Feldspar 50, Whiting 15, Silica 30, Kaolin 5, Copper Carbonate 5. Used Flint(P3319) as Silica, and Aluminium Oxide(P3300) instead of Kaolin, and Feldspar FFF(P3316) as Custer Feldspar."/>

   <glaze xml:id="ModifiedMamo"
           manufacturer="Frans Englich"
           name="ModifiedMamo"
           description="Mamo from The Complete Guide to High-Fire Glazes, p. 121. Custer Feldspar 25, F-4 Feldspar 25, Whiting 5, Kaolin 10, Calcined Kaolin 15, Dolomite 20. Due to lacking ingredients it was instead: Feldspar(P3316) 50, Whiting 5, Aluminium Oxide 35, Dolomite 20."/>

   <glaze xml:id="BlueModifiedMamo"
           manufacturer="Frans Englich"
           name="ModifiedMamo"
           description="Mamo from The Complete Guide to High-Fire Glazes, p. 121, with Cobolt. Custer Feldspar 25, F-4 Feldspar 25, Whiting 5, Kaolin 10, Calcined Kaolin 15, Dolomite 20. Due to lacking ingredients it was instead: Feldspar(P3316) 50, Whiting 5, Aluminium Oxide 35, Dolomite 20, 2 Cobolt Oxide."/>

   <!-- All for keramik, Cerama 6250. -->
</glazes>
<!--
vim: et:ts=4:sw=4:sts=4
-->
